hudi-0.4.0.dist-info/METADATA
hudi-0.4.0.dist-info/WHEEL
hudi/__init__.py
hudi/_internal.abi3.so
hudi/_internal.pyi
hudi/py.typed
hudi/table/__init__.py
hudi/table/builder.py
hudi-0.4.0.dist-info/RECORD
