Metadata-Version: 2.4
Name: hudi
Version: 0.4.0
Classifier: License :: OSI Approved :: Apache Software License
Classifier: Programming Language :: Python :: 3.9
Classifier: Programming Language :: Python :: 3.10
Classifier: Programming Language :: Python :: 3.11
Classifier: Programming Language :: Python :: 3.12
Classifier: Programming Language :: Python :: 3.13
Requires-Dist: pyarrow>=11.0.0
Requires-Dist: pyarrow-hotfix
Requires-Dist: pytest==8.3.5 ; extra == 'devel'
Requires-Dist: coverage==7.8 ; extra == 'devel'
Requires-Dist: ruff==0.12 ; extra == 'devel'
Requires-Dist: mypy==1.15 ; extra == 'devel'
Provides-Extra: devel
Summary: Native Python binding for Apache Hudi, based on hudi-rs.
Keywords: apachehudi,hudi,datalake,arrow
Home-Page: https://github.com/apache/hudi-rs
License: Apache License 2.0
Requires-Python: >=3.9
Project-URL: repository, https://github.com/apache/hudi-rs/tree/main/python/
